trajalign/__init__.py
trajalign/align.py
trajalign/average.py
trajalign/traj.py
trajectory_alignment-1.3.dist-info/LICENSE
trajectory_alignment-1.3.dist-info/METADATA
trajectory_alignment-1.3.dist-info/WHEEL
trajectory_alignment-1.3.dist-info/top_level.txt
trajectory_alignment-1.3.dist-info/RECORD
