Metadata-Version: 2.1
Name: trajectory-alignment
Version: 1.3
Summary: Utilities to Align and Average Trajectories
Home-page: http://apicco.github.io/trajectory_alignment/
Download-URL: https://github.com/apicco/trajectory_alignment/archive/master.zip
Author: Andrea Picco
Author-email: andrea.picco@unige.ch
License: The software is distributed under the terms of the GNU General Public License Version 3, June 2007. Trajalign is a free software and comes with ABSOLUTELY NO WARRANTY. You are welcome to redistribute the software. However, we appreciate is use of such software would result in citations of Picco, A., Kaksonen, M., _Precise tracking of the dynamics of multiple proteins in endocytic events_,  Methods in Cell Biology, Vol. 139, pages 51-68 (2017) http://www.sciencedirect.com/science/article
License-File: LICENSE
